radius.py
radius-0.0.4.dist-info/LICENSE
radius-0.0.4.dist-info/METADATA
radius-0.0.4.dist-info/WHEEL
radius-0.0.4.dist-info/top_level.txt
radius-0.0.4.dist-info/RECORD
