Metadata-Version: 1.2
Name: radius
Version: 0.0.4
Summary: RADIUS authentication module
Home-page: https://github.com/Osirium/py-radius/
Author: Stuart Bishop
Author-email: zen@shangri-la.dropbear.id.au
Maintainer: Osirium
Maintainer-email: thomas.grainger@osirium.net
License: UNKNOWN
Platform: UNKNOWN
Classifier: License :: OSI Approved :: MIT License
Classifier: Programming Language :: Python :: 2.7
Classifier: Programming Language :: Python :: 3.0
Classifier: Programming Language :: Python :: 3.1
Classifier: Programming Language :: Python :: 3.2
Classifier: Programming Language :: Python :: 3.3
Classifier: Programming Language :: Python :: 3.4
Classifier: Programming Language :: Python :: 3.5
Classifier: Programming Language :: Python :: 3.6
Classifier: Programming Language :: Python :: 3.7
Classifier: Topic :: Software Development :: Libraries :: Python Modules
Classifier: Topic :: System :: Systems Administration :: Authentication/Directory
